silvio/FermProSimFun.py
silvio/MetEngSimFun.py
silvio/__init__.py
silvio/config.py
silvio/events.py
silvio/experiment.py
silvio/host.py
silvio/module.py
silvio/outcome.py
silvio/random.py
silvio/record.py
silvio/registry.py
silvio/tool.py
silvio/utils.py
silvio/catalog/GroExpSim.py
silvio/catalog/RecExpSim.py
silvio/catalog/StrExpSim.py
silvio/catalog/__init__.py
silvio/data/CodonTriplets.csv
silvio/data/expression_predictor/Ecol-Promoter-AddParams.pkl
silvio/data/expression_predictor/Ecol-Promoter-predictor.pkl
silvio/data/expression_predictor/Ptai-Promoter-AddParams.pkl
silvio/data/expression_predictor/Ptai-Promoter-predictor.pkl
silvio/data/hplc/e_coli_core (1).json
silvio/data/hplc/e_coli_core.json
silvio/data/hplc/synthetic_LB_chromatogram.csv
silvio/data/hplc/test_hplc.ipynb
silvio/data/hplc/Data/e_coli_core.json
silvio/data/metabolic_model/e_coli_core.xml
silvio/data/metabolic_model/iJN746.xml
silvio/extensions/__init__.py
silvio/extensions/all_events.py
silvio/extensions/common.py
silvio/extensions/modules/__init__.py
silvio/extensions/modules/genome_expression.py
silvio/extensions/modules/genome_library.py
silvio/extensions/modules/genome_list.py
silvio/extensions/modules/growth_behaviour.py
silvio/extensions/modules/metabolic_flux.py
silvio/extensions/modules/metabolism.py
silvio/extensions/modules/phenotype_size.py
silvio/extensions/records/__init__.py
silvio/extensions/records/growth_record.py
silvio/extensions/records/gene/__init__.py
silvio/extensions/records/gene/crafted_gene.py
silvio/extensions/records/gene/gene.py
silvio/extensions/records/gene/localized_gene.py
silvio/extensions/records/gene/stub_gene.py
silvio/extensions/sets/__init__.py
silvio/extensions/sets/shotgun_sequencing/__init__.py
silvio/extensions/sets/shotgun_sequencing/assembly.py
silvio/extensions/sets/shotgun_sequencing/datatype.py
silvio/extensions/sets/shotgun_sequencing/evaluation.py
silvio/extensions/sets/shotgun_sequencing/sequencing.py
silvio-0.3.3.dist-info/licenses/AUTHORS.rst
silvio-0.3.3.dist-info/licenses/LICENSE
silvio-0.3.3.dist-info/METADATA
silvio-0.3.3.dist-info/WHEEL
silvio-0.3.3.dist-info/top_level.txt
silvio-0.3.3.dist-info/RECORD
